netbox_pyswagger/__init__.py
netbox_pyswagger/client.py
netbox_pyswagger-0.1.2.dist-info/DESCRIPTION.rst
netbox_pyswagger-0.1.2.dist-info/METADATA
netbox_pyswagger-0.1.2.dist-info/RECORD
netbox_pyswagger-0.1.2.dist-info/WHEEL
netbox_pyswagger-0.1.2.dist-info/metadata.json
netbox_pyswagger-0.1.2.dist-info/top_level.txt
