Metadata-Version: 2.0
Name: netbox-pyswagger
Version: 0.1.2
Summary: Swagger client for Netbox
Home-page: https://github.com/jeremyschulman/netbox-pyswagger
Author: Jeremy Schulman
Author-email: nwkautomaniac@gmail.com
License: MIT
Keywords: netbox,rest,json,api,network,automation
Platform: UNKNOWN
Classifier: Development Status :: 4 - Beta
Classifier: Intended Audience :: Developers
Classifier: License :: OSI Approved :: MIT License
Classifier: Programming Language :: Python :: 2.7
Requires-Dist: halutz (>=0.2.0)
Requires-Dist: requests
Requires-Dist: six
